ipack/__init__.py
ipack/getipynb.py
getipynb-1.0.dist-info/LICENSE
getipynb-1.0.dist-info/METADATA
getipynb-1.0.dist-info/WHEEL
getipynb-1.0.dist-info/top_level.txt
getipynb-1.0.dist-info/RECORD
