Metadata-Version: 2.1
Name: getipynb
Version: 1.0
Summary: Package to convert .py into jupyter executable notebook
Home-page: UNKNOWN
Author: arnavr
License: UNKNOWN
Keywords: python,jupyter,ipython
Platform: UNKNOWN
Classifier: Development Status :: 1 - Planning
Classifier: Intended Audience :: Developers
Classifier: Programming Language :: Python :: 3
Classifier: Operating System :: Unix
Classifier: Operating System :: MacOS :: MacOS X
Classifier: Operating System :: Microsoft :: Windows
License-File: LICENSE
